reprshed.py
reprshed-1.0.6.dist-info/LICENSE
reprshed-1.0.6.dist-info/METADATA
reprshed-1.0.6.dist-info/WHEEL
reprshed-1.0.6.dist-info/top_level.txt
reprshed-1.0.6.dist-info/RECORD
