Metadata-Version: 1.1
Name: reprshed
Version: 1.0.6
Summary: A toolshed for writing great ``__repr__`` methods quickly and easily.
Home-page: https://github.com/mentalisttraceur/python-reprshed
Author: Alexander Kozhevnikov
Author-email: mentalisttraceur@gmail.com
License: 0BSD
Platform: UNKNOWN
Classifier: Development Status :: 5 - Production/Stable
Classifier: Programming Language :: Python :: 3
Classifier: Programming Language :: Python :: 2
Classifier: Operating System :: OS Independent
